pxalyze/__init__.py
pxalyze-0.1.0.dist-info/licenses/LICENSE
pxalyze-0.1.0.dist-info/METADATA
pxalyze-0.1.0.dist-info/WHEEL
pxalyze-0.1.0.dist-info/top_level.txt
pxalyze-0.1.0.dist-info/RECORD
