Metadata-Version: 2.4
Name: pxalyze
Version: 0.1.0
Summary: Pxalyze - a single file for your computer vision debugging
Author-email: Ilia Moiseev <ilia.moiseev.5@yandex.ru>
License: Apache License, Version 2.0
Classifier: Programming Language :: Python :: 3
Classifier: Operating System :: OS Independent
Requires-Python: >=3.7
License-File: LICENSE
Requires-Dist: numpy
Provides-Extra: opencv
Requires-Dist: opencv-python; extra == "opencv"
Dynamic: license-file
